botwinick_gis/__init__.py
botwinick_gis-0.0.3.dist-info/LICENSE
botwinick_gis-0.0.3.dist-info/METADATA
botwinick_gis-0.0.3.dist-info/WHEEL
botwinick_gis-0.0.3.dist-info/top_level.txt
botwinick_gis-0.0.3.dist-info/RECORD
