Metadata-Version: 2.1
Name: botwinick-gis
Version: 0.0.3
Summary: GIS support package
Home-page: https://github.com/dbotwinick/python-botwinick-gis
Author: Drew Botwinick
Author-email: foss@drewbotwinick.com
License: UNKNOWN
Platform: UNKNOWN
Classifier: Development Status :: 4 - Beta
Classifier: Intended Audience :: Developers
Classifier: Topic :: Scientific/Engineering :: GIS
Classifier: Programming Language :: Python :: 2
Classifier: Programming Language :: Python :: 3
Classifier: License :: OSI Approved :: BSD License
Classifier: Operating System :: OS Independent
Requires-Python: >=2.7, >=3.6
Requires-Dist: numpy
Requires-Dist: pyshp
Requires-Dist: pyproj
Requires-Dist: botwinick-math
